LCoinPrice/CoinPrice.py
LCoinPrice/__init__.py
LCoinPrice-0.1.dist-info/METADATA
LCoinPrice-0.1.dist-info/WHEEL
LCoinPrice-0.1.dist-info/top_level.txt
LCoinPrice-0.1.dist-info/RECORD
