Metadata-Version: 2.1
Name: LCoinPrice
Version: 0.1
Requires-Dist: pycoingecko
